deem/testfixture/__init__.py
deem.testfixture-0.0.6.dist-info/LICENSE.txt
deem.testfixture-0.0.6.dist-info/METADATA
deem.testfixture-0.0.6.dist-info/WHEEL
deem.testfixture-0.0.6.dist-info/top_level.txt
deem.testfixture-0.0.6.dist-info/RECORD
