Metadata-Version: 2.1
Name: deem.testfixture
Version: 0.0.6
Summary: Python3 Deem Base Tests
Home-page: https://github.com/deem-team
Author: Alexander Eliseyev
Author-email: alex@deem.ai
License: MIT
Platform: UNKNOWN
Classifier: Development Status :: 3 - Alpha
Classifier: Intended Audience :: Developers
Classifier: License :: OSI Approved :: MIT License
Classifier: Programming Language :: Python :: 3
Classifier: Programming Language :: Python :: 3.4
Classifier: Programming Language :: Python :: 3.5
Classifier: Programming Language :: Python :: 3.6
